latex/__init__.py
latex/app.py
latex_hot_reload-1.0.9.dist-info/LICENSE
latex_hot_reload-1.0.9.dist-info/METADATA
latex_hot_reload-1.0.9.dist-info/WHEEL
latex_hot_reload-1.0.9.dist-info/entry_points.txt
latex_hot_reload-1.0.9.dist-info/top_level.txt
latex_hot_reload-1.0.9.dist-info/RECORD
