Metadata-Version: 2.1
Name: latex-hot-reload
Version: 1.0.9
Summary: Reloads LaTeX files on change
Author-email: Kaan Giray Buzluk <kaangiray26@protonmail.com>
License: MIT License
Project-URL: Homepage, https://github.com/kaangiray26/latex-hot-reload
Project-URL: Bug Tracker, https://github.com/kaangiray26/latex-hot-reload/issues
Classifier: Programming Language :: Python :: 3
Classifier: License :: OSI Approved :: GNU General Public License v3 (GPLv3)
Classifier: Operating System :: OS Independent
Requires-Python: >=3.8
License-File: LICENSE
Requires-Dist: watchfiles >=0.21.0
